torchlosses/__init__.py
torchlosses/contrastive.py
torchlosses/cosine.py
torchlosses/dice.py
torchlosses/focal.py
torchlosses/huber.py
torchlosses/kldiv.py
torchlosses/triplet.py
torchlosses-0.1.0.dist-info/METADATA
torchlosses-0.1.0.dist-info/WHEEL
torchlosses-0.1.0.dist-info/top_level.txt
torchlosses-0.1.0.dist-info/RECORD
